CHANGELOG.rst
LICENSE
MANIFEST.in
README.rst
requirements-dev.txt
requirements.txt
setup.py
FsnViz.egg-info/PKG-INFO
FsnViz.egg-info/SOURCES.txt
FsnViz.egg-info/dependency_links.txt
FsnViz.egg-info/entry_points.txt
FsnViz.egg-info/not-zip-safe
FsnViz.egg-info/requires.txt
FsnViz.egg-info/top_level.txt
fsnviz/__init__.py
fsnviz/cli.py
fsnviz/fusioncatcher.py
fsnviz/models.py
fsnviz/star_fusion.py
fsnviz/utils.py
fsnviz/templates/__init__.py
fsnviz/templates/circos.conf.j2
tests/__init__.py
tests/test_fusioncatcher.py
tests/test_general.py
tests/test_star_fusion.py
tests/utils.py
tests/cases/fusioncatcher_v0995a_01.txt
tests/cases/star_fusion_v060_01.txt