Metadata-Version: 1.1
Name: FsnViz
Version: 0.2.0
Summary: Tool for plotting gene fusion events detected by various tools using Circos.
Home-page: http://bow.web.id
Author: Wibowo Arindrarto
Author-email: bow@bow.web.id
License: BSD
Keywords: rnaseq fusion circos plot bioinformatics visualization
Platform: UNKNOWN
Classifier: Development Status :: 3 - Alpha
Classifier: Environment :: Console
Classifier: Intended Audience :: Developers
Classifier: Intended Audience :: Science/Research
Classifier: License :: OSI Approved :: BSD License
Classifier: Operating System :: POSIX
Classifier: Programming Language :: Python :: 3.5
Classifier: Topic :: Utilities
Classifier: Topic :: Scientific/Engineering :: Visualization
